{
    "fluentMethods": true,
    "clientRootFolder": "",
    "relationships": [],
    "fields": [
        {
            "fieldName": "name",
            "fieldType": "String",
            "fieldValidateRules": [
                "required"
            ]
        },
        {
            "fieldName": "phoneNumber",
            "fieldType": "String"
        },
        {
            "fieldName": "address",
            "fieldType": "String"
        },
        {
            "fieldName": "email",
            "fieldType": "String"
        }
    ],
    "changelogDate": "20180830095003",
    "dto": "no",
    "searchEngine": false,
    "service": "no",
    "entityTableName": "client",
    "jpaMetamodelFiltering": false,
    "pagination": "no"
}
